setup.py
xloger/__init__.py
xloger/client.py
xloger/vendors.py
xloger.egg-info/PKG-INFO
xloger.egg-info/SOURCES.txt
xloger.egg-info/dependency_links.txt
xloger.egg-info/not-zip-safe
xloger.egg-info/requires.txt
xloger.egg-info/top_level.txt