Metadata-Version: 1.1
Name: xloger
Version: 1.3.0
Summary: python client lib for xloger.
Home-page: https://github.com/idollo/xloger-python.git
Author: idollo
Author-email: stone58@qq.com
License: MIT
Platform: any
Classifier: Environment :: Web Environment
Classifier: Intended Audience :: Developers
Classifier: Programming Language :: Python
Classifier: Programming Language :: Python :: 2.7
Classifier: Programming Language :: Python :: 3
Classifier: Programming Language :: Python :: 3.3
Classifier: Programming Language :: Python :: 3.4
Classifier: Programming Language :: Python :: 3.5
